back_channel_client/__init__.py
back_channel_client/back_channel_client.py
back_channel_client/forward.py
back_channel_client-0.2.0.dist-info/METADATA
back_channel_client-0.2.0.dist-info/WHEEL
back_channel_client-0.2.0.dist-info/entry_points.txt
back_channel_client-0.2.0.dist-info/licenses/LICENSE
back_channel_client-0.2.0.dist-info/RECORD
