Metadata-Version: 2.4
Name: back-channel-client
Version: 0.2.0
Summary: Back channel client
Project-URL: Homepage, https://github.com/radaron/BackChannelClient
Author-email: Aron Radics <radics.aron.jozsef@gmail.com>
License-File: LICENSE
Classifier: License :: OSI Approved :: MIT License
Classifier: Operating System :: OS Independent
Classifier: Programming Language :: Python :: 3
Requires-Python: >=3.9
Requires-Dist: psutil>=5.8.0
Requires-Dist: requests>=2.28.1
